BunnyCDN/CDN.py
BunnyCDN/Storage.py
BunnyCDN/__init__.py
bunnycdnpython-0.0.8.dist-info/LICENSE
bunnycdnpython-0.0.8.dist-info/METADATA
bunnycdnpython-0.0.8.dist-info/WHEEL
bunnycdnpython-0.0.8.dist-info/top_level.txt
bunnycdnpython-0.0.8.dist-info/RECORD
