Metadata-Version: 2.1
Name: bunnycdnpython
Version: 0.0.8
Summary: A python SDK for BunnyCDN
Home-page: https://github.com/mathrithms/BunnyCDN-Python-Lib
Author: mathrithms
Author-email: hello@mathrithms.com
License: UNKNOWN
Platform: UNKNOWN
Classifier: Programming Language :: Python :: 3
Classifier: License :: OSI Approved :: MIT License
Classifier: Operating System :: OS Independent
Requires-Python: >=3.6
License-File: LICENSE
Requires-Dist: requests
